{"content":"+August 22,2020","terminals":[{"content":"+","type":10,"meta":{"content":"+","altpronunciation":"","altrecognition":""}},{"content":"August 22,2020","type":2,"meta":{"format":1,"month":{"content":"August","altpronunciation":"august","altrecognition":""},"punctuation1":{"content":"","altpronunciation":"","altrecognition":""},"whitespace1":{"content":" ","altpronunciation":"","altrecognition":""},"day":{"content":"22","altpronunciation":"22nd","altrecognition":""},"punctuation2":{"content":",","altpronunciation":"","altrecognition":""},"whitespace2":{"content":"","altpronunciation":"","altrecognition":""},"year":{"century":{"content":"20","altpronunciation":"(two thousand) | (twenty)","altrecognition":""},"withinCentury":{"content":"20","altpronunciation":"(twenty)","altrecognition":""}}}}]}