
{"Parser02":
  { "section": [
    {
     "id": 1, "name": "section 1", "date":"", "description":"", "owner": "Ronlyn", "sentence":
     [
       {"id":1,"content":"This is section 1's sentence 01"},
       {"id":2,"content":"This is section 1's sentence 02"},
       {"id":3,"content":"This is section 1's sentence 03"},
       {"id":4,"content":"This is section 1's sentence 04"},
       {"id":5,"content":"This is section 1's sentence 05"},
       {"id":6,"content":"This is section 1's sentence 06"}
     ] },
     {
      "id": 1, "name": "section 2", "date":"", "description":"", "owner": "Ronlyn", "sentence":
      [
        {"id":1,"content":"This is section 2's sentence 01"},
        {"id":2,"content":"This is section 2's sentence 02"},
        {"id":3,"content":"This is section 2's sentence 03"},
        {"id":4,"content":"This is section 2's sentence 04"},
        {"id":5,"content":"This is section 2's sentence 05"},
        {"id":6,"content":"This is section 2's sentence 06"}
      ] }
  ] }
}
