{
  "id": 0,
  "title": "",
  "filename": "links1.json",
  "description": "",
  "owner": "",
  "pageFormatType": 0,
  "created": "Fri Jan 28 2022 08:36:35 GMT-0800 (Pacific Standard Time)",
  "modified": "Fri Jan 28 2022 08:36:36 GMT-0800 (Pacific Standard Time)",
  "transformed": "Fri Jan 28 2022 08:36:36 GMT-0800 (Pacific Standard Time)",
  "firstTermIdx": -9999,
  "lastTermIdx": -9999,
  "sections": [
    {
      "id": 0,
      "name": "",
      "description": "",
      "firstTermIdx": 0,
      "lastTermIdx": 6,
      "items": [],
      "type": "paragraph",
      "meta": {
        "sentences": [
          {
            "id": 0,
            "content": "a link [and I'm at the start](link2, 6)",
            "firstTermIdx": 0,
            "lastTermIdx": 6,
            "terminals": [
              {
                "id": 0,
                "termIdx": 0,
                "content": "a",
                "firstTermIdx": 0,
                "lastTermIdx": 0,
                "type": 13,
                "meta": {
                  "content": "a",
                  "termIdx": 0,
                  "nextTermIdx": [
                    1
                  ],
                  "prevTermIdx": [],
                  "altpronunciation": "",
                  "altrecognition": "",
                  "recitable": true,
                  "audible": true,
                  "linkable": false,
                  "visible": true,
                  "fillin": false,
                  "visited": false,
                  "linkIdx": -9999,
                  "hintsIdx": -9999
                }
              },
              {
                "id": 0,
                "termIdx": -9999,
                "content": " ",
                "firstTermIdx": -9999,
                "lastTermIdx": -9999,
                "type": 12,
                "meta": {
                  "content": " ",
                  "termIdx": -9999,
                  "nextTermIdx": [],
                  "prevTermIdx": [],
                  "altpronunciation": "",
                  "altrecognition": "",
                  "recitable": false,
                  "audible": false,
                  "linkable": false,
                  "visible": true,
                  "fillin": false,
                  "visited": false,
                  "linkIdx": -9999,
                  "hintsIdx": -9999
                }
              },
              {
                "id": 0,
                "termIdx": 1,
                "content": "link",
                "firstTermIdx": 1,
                "lastTermIdx": 1,
                "type": 13,
                "meta": {
                  "content": "link",
                  "termIdx": 1,
                  "nextTermIdx": [
                    2
                  ],
                  "prevTermIdx": [
                    0
                  ],
                  "altpronunciation": "",
                  "altrecognition": "",
                  "recitable": true,
                  "audible": true,
                  "linkable": false,
                  "visible": true,
                  "fillin": false,
                  "visited": false,
                  "linkIdx": -9999,
                  "hintsIdx": -9999
                }
              },
              {
                "id": 0,
                "termIdx": -9999,
                "content": " ",
                "firstTermIdx": -9999,
                "lastTermIdx": -9999,
                "type": 12,
                "meta": {
                  "content": " ",
                  "termIdx": -9999,
                  "nextTermIdx": [],
                  "prevTermIdx": [],
                  "altpronunciation": "",
                  "altrecognition": "",
                  "recitable": false,
                  "audible": false,
                  "linkable": false,
                  "visible": true,
                  "fillin": false,
                  "visited": false,
                  "linkIdx": -9999,
                  "hintsIdx": -9999
                }
              },
              {
                "id": 0,
                "termIdx": -9999,
                "content": "and I'm at the start",
                "firstTermIdx": 2,
                "lastTermIdx": 6,
                "type": 5,
                "meta": {
                  "label": [
                    {
                      "id": 0,
                      "termIdx": 2,
                      "content": "and",
                      "firstTermIdx": 2,
                      "lastTermIdx": 2,
                      "type": 13,
                      "meta": {
                        "content": "and",
                        "termIdx": 2,
                        "nextTermIdx": [
                          3
                        ],
                        "prevTermIdx": [
                          1
                        ],
                        "altpronunciation": "",
                        "altrecognition": "",
                        "recitable": true,
                        "audible": true,
                        "linkable": false,
                        "visible": true,
                        "fillin": false,
                        "visited": false,
                        "linkIdx": -9999,
                        "hintsIdx": -9999
                      }
                    },
                    {
                      "id": 0,
                      "termIdx": -9999,
                      "content": " ",
                      "firstTermIdx": -9999,
                      "lastTermIdx": -9999,
                      "type": 12,
                      "meta": {
                        "content": " ",
                        "termIdx": -9999,
                        "nextTermIdx": [],
                        "prevTermIdx": [],
                        "altpronunciation": "",
                        "altrecognition": "",
                        "recitable": false,
                        "audible": false,
                        "linkable": false,
                        "visible": true,
                        "fillin": false,
                        "visited": false,
                        "linkIdx": -9999,
                        "hintsIdx": -9999
                      }
                    },
                    {
                      "id": 0,
                      "termIdx": 3,
                      "content": "I'm",
                      "firstTermIdx": 3,
                      "lastTermIdx": 3,
                      "type": 13,
                      "meta": {
                        "content": "I'm",
                        "termIdx": 3,
                        "nextTermIdx": [
                          4
                        ],
                        "prevTermIdx": [
                          2
                        ],
                        "altpronunciation": "",
                        "altrecognition": "",
                        "recitable": true,
                        "audible": true,
                        "linkable": false,
                        "visible": true,
                        "fillin": false,
                        "visited": false,
                        "linkIdx": -9999,
                        "hintsIdx": -9999
                      }
                    },
                    {
                      "id": 0,
                      "termIdx": -9999,
                      "content": " ",
                      "firstTermIdx": -9999,
                      "lastTermIdx": -9999,
                      "type": 12,
                      "meta": {
                        "content": " ",
                        "termIdx": -9999,
                        "nextTermIdx": [],
                        "prevTermIdx": [],
                        "altpronunciation": "",
                        "altrecognition": "",
                        "recitable": false,
                        "audible": false,
                        "linkable": false,
                        "visible": true,
                        "fillin": false,
                        "visited": false,
                        "linkIdx": -9999,
                        "hintsIdx": -9999
                      }
                    },
                    {
                      "id": 0,
                      "termIdx": 4,
                      "content": "at",
                      "firstTermIdx": 4,
                      "lastTermIdx": 4,
                      "type": 13,
                      "meta": {
                        "content": "at",
                        "termIdx": 4,
                        "nextTermIdx": [
                          5
                        ],
                        "prevTermIdx": [
                          3
                        ],
                        "altpronunciation": "",
                        "altrecognition": "",
                        "recitable": true,
                        "audible": true,
                        "linkable": false,
                        "visible": true,
                        "fillin": false,
                        "visited": false,
                        "linkIdx": -9999,
                        "hintsIdx": -9999
                      }
                    },
                    {
                      "id": 0,
                      "termIdx": -9999,
                      "content": " ",
                      "firstTermIdx": -9999,
                      "lastTermIdx": -9999,
                      "type": 12,
                      "meta": {
                        "content": " ",
                        "termIdx": -9999,
                        "nextTermIdx": [],
                        "prevTermIdx": [],
                        "altpronunciation": "",
                        "altrecognition": "",
                        "recitable": false,
                        "audible": false,
                        "linkable": false,
                        "visible": true,
                        "fillin": false,
                        "visited": false,
                        "linkIdx": -9999,
                        "hintsIdx": -9999
                      }
                    },
                    {
                      "id": 0,
                      "termIdx": 5,
                      "content": "the",
                      "firstTermIdx": 5,
                      "lastTermIdx": 5,
                      "type": 13,
                      "meta": {
                        "content": "the",
                        "termIdx": 5,
                        "nextTermIdx": [
                          6
                        ],
                        "prevTermIdx": [
                          4
                        ],
                        "altpronunciation": "",
                        "altrecognition": "",
                        "recitable": true,
                        "audible": true,
                        "linkable": false,
                        "visible": true,
                        "fillin": false,
                        "visited": false,
                        "linkIdx": -9999,
                        "hintsIdx": -9999
                      }
                    },
                    {
                      "id": 0,
                      "termIdx": -9999,
                      "content": " ",
                      "firstTermIdx": -9999,
                      "lastTermIdx": -9999,
                      "type": 12,
                      "meta": {
                        "content": " ",
                        "termIdx": -9999,
                        "nextTermIdx": [],
                        "prevTermIdx": [],
                        "altpronunciation": "",
                        "altrecognition": "",
                        "recitable": false,
                        "audible": false,
                        "linkable": false,
                        "visible": true,
                        "fillin": false,
                        "visited": false,
                        "linkIdx": -9999,
                        "hintsIdx": -9999
                      }
                    },
                    {
                      "id": 0,
                      "termIdx": 6,
                      "content": "start",
                      "firstTermIdx": 6,
                      "lastTermIdx": 6,
                      "type": 13,
                      "meta": {
                        "content": "start",
                        "termIdx": 6,
                        "nextTermIdx": [
                          7
                        ],
                        "prevTermIdx": [
                          5
                        ],
                        "altpronunciation": "",
                        "altrecognition": "",
                        "recitable": true,
                        "audible": true,
                        "linkable": false,
                        "visible": true,
                        "fillin": false,
                        "visited": false,
                        "linkIdx": -9999,
                        "hintsIdx": -9999
                      }
                    }
                  ],
                  "destination": {
                    "page": "link2",
                    "directory": "",
                    "sectionIdx": 6,
                    "terminalIdx": -9999
                  },
                  "className": "",
                  "style": "",
                  "linkIdx": 0
                }
              }
            ],
            "lastPunctuation": ""
          }
        ],
        "style": ""
      }
    },
    {
      "id": 1,
      "name": "",
      "description": "",
      "firstTermIdx": 7,
      "lastTermIdx": 10,
      "items": [],
      "type": "paragraph",
      "meta": {
        "sentences": [
          {
            "id": 1,
            "content": "[I'm at the start](test2, 1)",
            "firstTermIdx": 7,
            "lastTermIdx": 10,
            "terminals": [
              {
                "id": 0,
                "termIdx": -9999,
                "content": "I'm at the start",
                "firstTermIdx": 7,
                "lastTermIdx": 10,
                "type": 5,
                "meta": {
                  "label": [
                    {
                      "id": 0,
                      "termIdx": 7,
                      "content": "I'm",
                      "firstTermIdx": 7,
                      "lastTermIdx": 7,
                      "type": 13,
                      "meta": {
                        "content": "I'm",
                        "termIdx": 7,
                        "nextTermIdx": [
                          8
                        ],
                        "prevTermIdx": [
                          6
                        ],
                        "altpronunciation": "",
                        "altrecognition": "",
                        "recitable": true,
                        "audible": true,
                        "linkable": false,
                        "visible": true,
                        "fillin": false,
                        "visited": false,
                        "linkIdx": -9999,
                        "hintsIdx": -9999
                      }
                    },
                    {
                      "id": 0,
                      "termIdx": -9999,
                      "content": " ",
                      "firstTermIdx": -9999,
                      "lastTermIdx": -9999,
                      "type": 12,
                      "meta": {
                        "content": " ",
                        "termIdx": -9999,
                        "nextTermIdx": [],
                        "prevTermIdx": [],
                        "altpronunciation": "",
                        "altrecognition": "",
                        "recitable": false,
                        "audible": false,
                        "linkable": false,
                        "visible": true,
                        "fillin": false,
                        "visited": false,
                        "linkIdx": -9999,
                        "hintsIdx": -9999
                      }
                    },
                    {
                      "id": 0,
                      "termIdx": 8,
                      "content": "at",
                      "firstTermIdx": 8,
                      "lastTermIdx": 8,
                      "type": 13,
                      "meta": {
                        "content": "at",
                        "termIdx": 8,
                        "nextTermIdx": [
                          9
                        ],
                        "prevTermIdx": [
                          7
                        ],
                        "altpronunciation": "",
                        "altrecognition": "",
                        "recitable": true,
                        "audible": true,
                        "linkable": false,
                        "visible": true,
                        "fillin": false,
                        "visited": false,
                        "linkIdx": -9999,
                        "hintsIdx": -9999
                      }
                    },
                    {
                      "id": 0,
                      "termIdx": -9999,
                      "content": " ",
                      "firstTermIdx": -9999,
                      "lastTermIdx": -9999,
                      "type": 12,
                      "meta": {
                        "content": " ",
                        "termIdx": -9999,
                        "nextTermIdx": [],
                        "prevTermIdx": [],
                        "altpronunciation": "",
                        "altrecognition": "",
                        "recitable": false,
                        "audible": false,
                        "linkable": false,
                        "visible": true,
                        "fillin": false,
                        "visited": false,
                        "linkIdx": -9999,
                        "hintsIdx": -9999
                      }
                    },
                    {
                      "id": 0,
                      "termIdx": 9,
                      "content": "the",
                      "firstTermIdx": 9,
                      "lastTermIdx": 9,
                      "type": 13,
                      "meta": {
                        "content": "the",
                        "termIdx": 9,
                        "nextTermIdx": [
                          10
                        ],
                        "prevTermIdx": [
                          8
                        ],
                        "altpronunciation": "",
                        "altrecognition": "",
                        "recitable": true,
                        "audible": true,
                        "linkable": false,
                        "visible": true,
                        "fillin": false,
                        "visited": false,
                        "linkIdx": -9999,
                        "hintsIdx": -9999
                      }
                    },
                    {
                      "id": 0,
                      "termIdx": -9999,
                      "content": " ",
                      "firstTermIdx": -9999,
                      "lastTermIdx": -9999,
                      "type": 12,
                      "meta": {
                        "content": " ",
                        "termIdx": -9999,
                        "nextTermIdx": [],
                        "prevTermIdx": [],
                        "altpronunciation": "",
                        "altrecognition": "",
                        "recitable": false,
                        "audible": false,
                        "linkable": false,
                        "visible": true,
                        "fillin": false,
                        "visited": false,
                        "linkIdx": -9999,
                        "hintsIdx": -9999
                      }
                    },
                    {
                      "id": 0,
                      "termIdx": 10,
                      "content": "start",
                      "firstTermIdx": 10,
                      "lastTermIdx": 10,
                      "type": 13,
                      "meta": {
                        "content": "start",
                        "termIdx": 10,
                        "nextTermIdx": [
                          11
                        ],
                        "prevTermIdx": [
                          9
                        ],
                        "altpronunciation": "",
                        "altrecognition": "",
                        "recitable": true,
                        "audible": true,
                        "linkable": false,
                        "visible": true,
                        "fillin": false,
                        "visited": false,
                        "linkIdx": -9999,
                        "hintsIdx": -9999
                      }
                    }
                  ],
                  "destination": {
                    "page": "test2",
                    "directory": "",
                    "sectionIdx": 1,
                    "terminalIdx": -9999
                  },
                  "className": "",
                  "style": "",
                  "linkIdx": 1
                }
              }
            ],
            "lastPunctuation": ""
          }
        ],
        "style": ""
      }
    },
    {
      "id": 2,
      "name": "",
      "description": "",
      "firstTermIdx": 11,
      "lastTermIdx": 15,
      "items": [],
      "type": "paragraph",
      "meta": {
        "sentences": [
          {
            "id": 2,
            "content": "the [at the start I'm](test2)",
            "firstTermIdx": 11,
            "lastTermIdx": 15,
            "terminals": [
              {
                "id": 0,
                "termIdx": 11,
                "content": "the",
                "firstTermIdx": 11,
                "lastTermIdx": 11,
                "type": 13,
                "meta": {
                  "content": "the",
                  "termIdx": 11,
                  "nextTermIdx": [
                    12
                  ],
                  "prevTermIdx": [
                    10
                  ],
                  "altpronunciation": "",
                  "altrecognition": "",
                  "recitable": true,
                  "audible": true,
                  "linkable": false,
                  "visible": true,
                  "fillin": false,
                  "visited": false,
                  "linkIdx": -9999,
                  "hintsIdx": -9999
                }
              },
              {
                "id": 0,
                "termIdx": -9999,
                "content": " ",
                "firstTermIdx": -9999,
                "lastTermIdx": -9999,
                "type": 12,
                "meta": {
                  "content": " ",
                  "termIdx": -9999,
                  "nextTermIdx": [],
                  "prevTermIdx": [],
                  "altpronunciation": "",
                  "altrecognition": "",
                  "recitable": false,
                  "audible": false,
                  "linkable": false,
                  "visible": true,
                  "fillin": false,
                  "visited": false,
                  "linkIdx": -9999,
                  "hintsIdx": -9999
                }
              },
              {
                "id": 0,
                "termIdx": -9999,
                "content": "at the start I'm",
                "firstTermIdx": 12,
                "lastTermIdx": 15,
                "type": 5,
                "meta": {
                  "label": [
                    {
                      "id": 0,
                      "termIdx": 12,
                      "content": "at",
                      "firstTermIdx": 12,
                      "lastTermIdx": 12,
                      "type": 13,
                      "meta": {
                        "content": "at",
                        "termIdx": 12,
                        "nextTermIdx": [
                          13
                        ],
                        "prevTermIdx": [
                          11
                        ],
                        "altpronunciation": "",
                        "altrecognition": "",
                        "recitable": true,
                        "audible": true,
                        "linkable": false,
                        "visible": true,
                        "fillin": false,
                        "visited": false,
                        "linkIdx": -9999,
                        "hintsIdx": -9999
                      }
                    },
                    {
                      "id": 0,
                      "termIdx": -9999,
                      "content": " ",
                      "firstTermIdx": -9999,
                      "lastTermIdx": -9999,
                      "type": 12,
                      "meta": {
                        "content": " ",
                        "termIdx": -9999,
                        "nextTermIdx": [],
                        "prevTermIdx": [],
                        "altpronunciation": "",
                        "altrecognition": "",
                        "recitable": false,
                        "audible": false,
                        "linkable": false,
                        "visible": true,
                        "fillin": false,
                        "visited": false,
                        "linkIdx": -9999,
                        "hintsIdx": -9999
                      }
                    },
                    {
                      "id": 0,
                      "termIdx": 13,
                      "content": "the",
                      "firstTermIdx": 13,
                      "lastTermIdx": 13,
                      "type": 13,
                      "meta": {
                        "content": "the",
                        "termIdx": 13,
                        "nextTermIdx": [
                          14
                        ],
                        "prevTermIdx": [
                          12
                        ],
                        "altpronunciation": "",
                        "altrecognition": "",
                        "recitable": true,
                        "audible": true,
                        "linkable": false,
                        "visible": true,
                        "fillin": false,
                        "visited": false,
                        "linkIdx": -9999,
                        "hintsIdx": -9999
                      }
                    },
                    {
                      "id": 0,
                      "termIdx": -9999,
                      "content": " ",
                      "firstTermIdx": -9999,
                      "lastTermIdx": -9999,
                      "type": 12,
                      "meta": {
                        "content": " ",
                        "termIdx": -9999,
                        "nextTermIdx": [],
                        "prevTermIdx": [],
                        "altpronunciation": "",
                        "altrecognition": "",
                        "recitable": false,
                        "audible": false,
                        "linkable": false,
                        "visible": true,
                        "fillin": false,
                        "visited": false,
                        "linkIdx": -9999,
                        "hintsIdx": -9999
                      }
                    },
                    {
                      "id": 0,
                      "termIdx": 14,
                      "content": "start",
                      "firstTermIdx": 14,
                      "lastTermIdx": 14,
                      "type": 13,
                      "meta": {
                        "content": "start",
                        "termIdx": 14,
                        "nextTermIdx": [
                          15
                        ],
                        "prevTermIdx": [
                          13
                        ],
                        "altpronunciation": "",
                        "altrecognition": "",
                        "recitable": true,
                        "audible": true,
                        "linkable": false,
                        "visible": true,
                        "fillin": false,
                        "visited": false,
                        "linkIdx": -9999,
                        "hintsIdx": -9999
                      }
                    },
                    {
                      "id": 0,
                      "termIdx": -9999,
                      "content": " ",
                      "firstTermIdx": -9999,
                      "lastTermIdx": -9999,
                      "type": 12,
                      "meta": {
                        "content": " ",
                        "termIdx": -9999,
                        "nextTermIdx": [],
                        "prevTermIdx": [],
                        "altpronunciation": "",
                        "altrecognition": "",
                        "recitable": false,
                        "audible": false,
                        "linkable": false,
                        "visible": true,
                        "fillin": false,
                        "visited": false,
                        "linkIdx": -9999,
                        "hintsIdx": -9999
                      }
                    },
                    {
                      "id": 0,
                      "termIdx": 15,
                      "content": "I'm",
                      "firstTermIdx": 15,
                      "lastTermIdx": 15,
                      "type": 13,
                      "meta": {
                        "content": "I'm",
                        "termIdx": 15,
                        "nextTermIdx": [
                          16
                        ],
                        "prevTermIdx": [
                          14
                        ],
                        "altpronunciation": "",
                        "altrecognition": "",
                        "recitable": true,
                        "audible": true,
                        "linkable": false,
                        "visible": true,
                        "fillin": false,
                        "visited": false,
                        "linkIdx": -9999,
                        "hintsIdx": -9999
                      }
                    }
                  ],
                  "destination": {
                    "page": "test2",
                    "directory": "",
                    "sectionIdx": -9999,
                    "terminalIdx": -9999
                  },
                  "className": "",
                  "style": "",
                  "linkIdx": 2
                }
              }
            ],
            "lastPunctuation": ""
          }
        ],
        "style": ""
      }
    },
    {
      "id": 3,
      "name": "",
      "description": "",
      "firstTermIdx": 16,
      "lastTermIdx": 26,
      "items": [],
      "type": "paragraph",
      "meta": {
        "sentences": [
          {
            "id": 3,
            "content": "[(308) 267-6076](,13) the",
            "firstTermIdx": 16,
            "lastTermIdx": 26,
            "terminals": [
              {
                "id": 0,
                "termIdx": -9999,
                "content": "(308) 267-6076",
                "firstTermIdx": -9999,
                "lastTermIdx": -9999,
                "type": 5,
                "meta": {
                  "label": [
                    {
                      "id": 0,
                      "termIdx": -9999,
                      "content": "(308) 267-6076",
                      "firstTermIdx": 16,
                      "lastTermIdx": 25,
                      "type": 7,
                      "meta": {
                        "countryCode": {
                          "content": "",
                          "termIdx": -9999,
                          "nextTermIdx": [],
                          "prevTermIdx": [],
                          "altpronunciation": "",
                          "altrecognition": "",
                          "recitable": true,
                          "audible": true,
                          "linkable": false,
                          "visible": true,
                          "fillin": false,
                          "visited": false,
                          "linkIdx": -9999,
                          "hintsIdx": -9999
                        },
                        "openBracket": {
                          "content": "(",
                          "termIdx": -9999,
                          "nextTermIdx": [],
                          "prevTermIdx": [],
                          "altpronunciation": "",
                          "altrecognition": "",
                          "recitable": false,
                          "audible": false,
                          "linkable": false,
                          "visible": true,
                          "fillin": false,
                          "visited": false,
                          "linkIdx": -9999,
                          "hintsIdx": -9999
                        },
                        "areaCode": [
                          {
                            "content": "3",
                            "termIdx": 16,
                            "nextTermIdx": [
                              17
                            ],
                            "prevTermIdx": [
                              15
                            ],
                            "altpronunciation": "",
                            "altrecognition": "",
                            "recitable": true,
                            "audible": true,
                            "linkable": false,
                            "visible": true,
                            "fillin": false,
                            "visited": false,
                            "linkIdx": -9999,
                            "hintsIdx": -9999
                          },
                          {
                            "content": "0",
                            "termIdx": 17,
                            "nextTermIdx": [
                              18
                            ],
                            "prevTermIdx": [
                              16
                            ],
                            "altpronunciation": "",
                            "altrecognition": "",
                            "recitable": true,
                            "audible": true,
                            "linkable": false,
                            "visible": true,
                            "fillin": false,
                            "visited": false,
                            "linkIdx": -9999,
                            "hintsIdx": -9999
                          },
                          {
                            "content": "8",
                            "termIdx": 18,
                            "nextTermIdx": [
                              19
                            ],
                            "prevTermIdx": [
                              17
                            ],
                            "altpronunciation": "",
                            "altrecognition": "",
                            "recitable": true,
                            "audible": true,
                            "linkable": false,
                            "visible": true,
                            "fillin": false,
                            "visited": false,
                            "linkIdx": -9999,
                            "hintsIdx": -9999
                          }
                        ],
                        "closeBracket": {
                          "content": ")",
                          "termIdx": -9999,
                          "nextTermIdx": [],
                          "prevTermIdx": [],
                          "altpronunciation": "",
                          "altrecognition": "",
                          "recitable": false,
                          "audible": false,
                          "linkable": false,
                          "visible": true,
                          "fillin": false,
                          "visited": false,
                          "linkIdx": -9999,
                          "hintsIdx": -9999
                        },
                        "separator1": {
                          "content": " ",
                          "termIdx": -9999,
                          "nextTermIdx": [],
                          "prevTermIdx": [],
                          "altpronunciation": "",
                          "altrecognition": "",
                          "recitable": false,
                          "audible": false,
                          "linkable": false,
                          "visible": true,
                          "fillin": false,
                          "visited": false,
                          "linkIdx": -9999,
                          "hintsIdx": -9999
                        },
                        "exchangeCode": [
                          {
                            "content": "2",
                            "termIdx": 19,
                            "nextTermIdx": [
                              20
                            ],
                            "prevTermIdx": [
                              18
                            ],
                            "altpronunciation": "",
                            "altrecognition": "",
                            "recitable": true,
                            "audible": true,
                            "linkable": false,
                            "visible": true,
                            "fillin": false,
                            "visited": false,
                            "linkIdx": -9999,
                            "hintsIdx": -9999
                          },
                          {
                            "content": "6",
                            "termIdx": 20,
                            "nextTermIdx": [
                              21
                            ],
                            "prevTermIdx": [
                              19
                            ],
                            "altpronunciation": "",
                            "altrecognition": "",
                            "recitable": true,
                            "audible": true,
                            "linkable": false,
                            "visible": true,
                            "fillin": false,
                            "visited": false,
                            "linkIdx": -9999,
                            "hintsIdx": -9999
                          },
                          {
                            "content": "7",
                            "termIdx": 21,
                            "nextTermIdx": [
                              22
                            ],
                            "prevTermIdx": [
                              20
                            ],
                            "altpronunciation": "",
                            "altrecognition": "",
                            "recitable": true,
                            "audible": true,
                            "linkable": false,
                            "visible": true,
                            "fillin": false,
                            "visited": false,
                            "linkIdx": -9999,
                            "hintsIdx": -9999
                          }
                        ],
                        "separator2": {
                          "content": "-",
                          "termIdx": -9999,
                          "nextTermIdx": [],
                          "prevTermIdx": [],
                          "altpronunciation": "",
                          "altrecognition": "",
                          "recitable": false,
                          "audible": false,
                          "linkable": false,
                          "visible": true,
                          "fillin": false,
                          "visited": false,
                          "linkIdx": -9999,
                          "hintsIdx": -9999
                        },
                        "lineNumber": [
                          {
                            "content": "6",
                            "termIdx": 22,
                            "nextTermIdx": [
                              23
                            ],
                            "prevTermIdx": [
                              21
                            ],
                            "altpronunciation": "",
                            "altrecognition": "",
                            "recitable": true,
                            "audible": true,
                            "linkable": false,
                            "visible": true,
                            "fillin": false,
                            "visited": false,
                            "linkIdx": -9999,
                            "hintsIdx": -9999
                          },
                          {
                            "content": "0",
                            "termIdx": 23,
                            "nextTermIdx": [
                              24
                            ],
                            "prevTermIdx": [
                              22
                            ],
                            "altpronunciation": "",
                            "altrecognition": "",
                            "recitable": true,
                            "audible": true,
                            "linkable": false,
                            "visible": true,
                            "fillin": false,
                            "visited": false,
                            "linkIdx": -9999,
                            "hintsIdx": -9999
                          },
                          {
                            "content": "7",
                            "termIdx": 24,
                            "nextTermIdx": [
                              25
                            ],
                            "prevTermIdx": [
                              23
                            ],
                            "altpronunciation": "",
                            "altrecognition": "",
                            "recitable": true,
                            "audible": true,
                            "linkable": false,
                            "visible": true,
                            "fillin": false,
                            "visited": false,
                            "linkIdx": -9999,
                            "hintsIdx": -9999
                          },
                          {
                            "content": "6",
                            "termIdx": 25,
                            "nextTermIdx": [
                              26
                            ],
                            "prevTermIdx": [
                              24
                            ],
                            "altpronunciation": "",
                            "altrecognition": "",
                            "recitable": true,
                            "audible": true,
                            "linkable": false,
                            "visible": true,
                            "fillin": false,
                            "visited": false,
                            "linkIdx": -9999,
                            "hintsIdx": -9999
                          }
                        ]
                      }
                    }
                  ],
                  "destination": {
                    "page": "",
                    "directory": "",
                    "sectionIdx": 13,
                    "terminalIdx": -9999
                  },
                  "className": "",
                  "style": "",
                  "linkIdx": 3
                }
              },
              {
                "id": 0,
                "termIdx": -9999,
                "content": " ",
                "firstTermIdx": -9999,
                "lastTermIdx": -9999,
                "type": 12,
                "meta": {
                  "content": " ",
                  "termIdx": -9999,
                  "nextTermIdx": [],
                  "prevTermIdx": [],
                  "altpronunciation": "",
                  "altrecognition": "",
                  "recitable": false,
                  "audible": false,
                  "linkable": false,
                  "visible": true,
                  "fillin": false,
                  "visited": false,
                  "linkIdx": -9999,
                  "hintsIdx": -9999
                }
              },
              {
                "id": 0,
                "termIdx": 26,
                "content": "the",
                "firstTermIdx": 26,
                "lastTermIdx": 26,
                "type": 13,
                "meta": {
                  "content": "the",
                  "termIdx": 26,
                  "nextTermIdx": [],
                  "prevTermIdx": [
                    25
                  ],
                  "altpronunciation": "",
                  "altrecognition": "",
                  "recitable": true,
                  "audible": true,
                  "linkable": false,
                  "visible": true,
                  "fillin": false,
                  "visited": false,
                  "linkIdx": -9999,
                  "hintsIdx": -9999
                }
              }
            ],
            "lastPunctuation": ""
          }
        ],
        "style": ""
      }
    },
    {
      "id": 0,
      "name": "",
      "description": "",
      "firstTermIdx": -9999,
      "lastTermIdx": -9999,
      "items": [],
      "type": "empty",
      "meta": {
        "count": 1
      }
    }
  ],
  "terminalList": [
    {
      "content": "a",
      "termIdx": 0,
      "nextTermIdx": [
        1
      ],
      "prevTermIdx": [],
      "altpronunciation": "",
      "altrecognition": "",
      "recitable": true,
      "audible": true,
      "linkable": false,
      "visible": true,
      "fillin": false,
      "visited": false,
      "linkIdx": -9999,
      "hintsIdx": -9999,
      "sentenceIdx": 0,
      "sectionIdx": 0
    },
    {
      "content": "link",
      "termIdx": 1,
      "nextTermIdx": [
        2
      ],
      "prevTermIdx": [
        0
      ],
      "altpronunciation": "",
      "altrecognition": "",
      "recitable": true,
      "audible": true,
      "linkable": false,
      "visible": true,
      "fillin": false,
      "visited": false,
      "linkIdx": -9999,
      "hintsIdx": -9999,
      "sentenceIdx": 0,
      "sectionIdx": 0
    },
    {
      "content": "and",
      "termIdx": 2,
      "nextTermIdx": [
        3
      ],
      "prevTermIdx": [
        1
      ],
      "altpronunciation": "",
      "altrecognition": "",
      "recitable": true,
      "audible": true,
      "linkable": false,
      "visible": true,
      "fillin": false,
      "visited": false,
      "linkIdx": 0,
      "hintsIdx": -9999,
      "sentenceIdx": 0,
      "sectionIdx": 0
    },
    {
      "content": "I'm",
      "termIdx": 3,
      "nextTermIdx": [
        4
      ],
      "prevTermIdx": [
        2
      ],
      "altpronunciation": "",
      "altrecognition": "",
      "recitable": true,
      "audible": true,
      "linkable": false,
      "visible": true,
      "fillin": false,
      "visited": false,
      "linkIdx": 0,
      "hintsIdx": -9999,
      "sentenceIdx": 0,
      "sectionIdx": 0
    },
    {
      "content": "at",
      "termIdx": 4,
      "nextTermIdx": [
        5
      ],
      "prevTermIdx": [
        3
      ],
      "altpronunciation": "",
      "altrecognition": "",
      "recitable": true,
      "audible": true,
      "linkable": false,
      "visible": true,
      "fillin": false,
      "visited": false,
      "linkIdx": 0,
      "hintsIdx": -9999,
      "sentenceIdx": 0,
      "sectionIdx": 0
    },
    {
      "content": "the",
      "termIdx": 5,
      "nextTermIdx": [
        6
      ],
      "prevTermIdx": [
        4
      ],
      "altpronunciation": "",
      "altrecognition": "",
      "recitable": true,
      "audible": true,
      "linkable": false,
      "visible": true,
      "fillin": false,
      "visited": false,
      "linkIdx": 0,
      "hintsIdx": -9999,
      "sentenceIdx": 0,
      "sectionIdx": 0
    },
    {
      "content": "start",
      "termIdx": 6,
      "nextTermIdx": [
        7
      ],
      "prevTermIdx": [
        5
      ],
      "altpronunciation": "",
      "altrecognition": "",
      "recitable": true,
      "audible": true,
      "linkable": false,
      "visible": true,
      "fillin": false,
      "visited": false,
      "linkIdx": 0,
      "hintsIdx": -9999,
      "sentenceIdx": 0,
      "sectionIdx": 0
    },
    {
      "content": "I'm",
      "termIdx": 7,
      "nextTermIdx": [
        8
      ],
      "prevTermIdx": [
        6
      ],
      "altpronunciation": "",
      "altrecognition": "",
      "recitable": true,
      "audible": true,
      "linkable": false,
      "visible": true,
      "fillin": false,
      "visited": false,
      "linkIdx": 1,
      "hintsIdx": -9999,
      "sentenceIdx": 1,
      "sectionIdx": 1
    },
    {
      "content": "at",
      "termIdx": 8,
      "nextTermIdx": [
        9
      ],
      "prevTermIdx": [
        7
      ],
      "altpronunciation": "",
      "altrecognition": "",
      "recitable": true,
      "audible": true,
      "linkable": false,
      "visible": true,
      "fillin": false,
      "visited": false,
      "linkIdx": 1,
      "hintsIdx": -9999,
      "sentenceIdx": 1,
      "sectionIdx": 1
    },
    {
      "content": "the",
      "termIdx": 9,
      "nextTermIdx": [
        10
      ],
      "prevTermIdx": [
        8
      ],
      "altpronunciation": "",
      "altrecognition": "",
      "recitable": true,
      "audible": true,
      "linkable": false,
      "visible": true,
      "fillin": false,
      "visited": false,
      "linkIdx": 1,
      "hintsIdx": -9999,
      "sentenceIdx": 1,
      "sectionIdx": 1
    },
    {
      "content": "start",
      "termIdx": 10,
      "nextTermIdx": [
        11
      ],
      "prevTermIdx": [
        9
      ],
      "altpronunciation": "",
      "altrecognition": "",
      "recitable": true,
      "audible": true,
      "linkable": false,
      "visible": true,
      "fillin": false,
      "visited": false,
      "linkIdx": 1,
      "hintsIdx": -9999,
      "sentenceIdx": 1,
      "sectionIdx": 1
    },
    {
      "content": "the",
      "termIdx": 11,
      "nextTermIdx": [
        12
      ],
      "prevTermIdx": [
        10
      ],
      "altpronunciation": "",
      "altrecognition": "",
      "recitable": true,
      "audible": true,
      "linkable": false,
      "visible": true,
      "fillin": false,
      "visited": false,
      "linkIdx": -9999,
      "hintsIdx": -9999,
      "sentenceIdx": 2,
      "sectionIdx": 2
    },
    {
      "content": "at",
      "termIdx": 12,
      "nextTermIdx": [
        13
      ],
      "prevTermIdx": [
        11
      ],
      "altpronunciation": "",
      "altrecognition": "",
      "recitable": true,
      "audible": true,
      "linkable": false,
      "visible": true,
      "fillin": false,
      "visited": false,
      "linkIdx": 2,
      "hintsIdx": -9999,
      "sentenceIdx": 2,
      "sectionIdx": 2
    },
    {
      "content": "the",
      "termIdx": 13,
      "nextTermIdx": [
        14
      ],
      "prevTermIdx": [
        12
      ],
      "altpronunciation": "",
      "altrecognition": "",
      "recitable": true,
      "audible": true,
      "linkable": false,
      "visible": true,
      "fillin": false,
      "visited": false,
      "linkIdx": 2,
      "hintsIdx": -9999,
      "sentenceIdx": 2,
      "sectionIdx": 2
    },
    {
      "content": "start",
      "termIdx": 14,
      "nextTermIdx": [
        15
      ],
      "prevTermIdx": [
        13
      ],
      "altpronunciation": "",
      "altrecognition": "",
      "recitable": true,
      "audible": true,
      "linkable": false,
      "visible": true,
      "fillin": false,
      "visited": false,
      "linkIdx": 2,
      "hintsIdx": -9999,
      "sentenceIdx": 2,
      "sectionIdx": 2
    },
    {
      "content": "I'm",
      "termIdx": 15,
      "nextTermIdx": [
        16
      ],
      "prevTermIdx": [
        14
      ],
      "altpronunciation": "",
      "altrecognition": "",
      "recitable": true,
      "audible": true,
      "linkable": false,
      "visible": true,
      "fillin": false,
      "visited": false,
      "linkIdx": 2,
      "hintsIdx": -9999,
      "sentenceIdx": 2,
      "sectionIdx": 2
    },
    {
      "content": "3",
      "termIdx": 16,
      "nextTermIdx": [
        17
      ],
      "prevTermIdx": [
        15
      ],
      "altpronunciation": "",
      "altrecognition": "",
      "recitable": true,
      "audible": true,
      "linkable": false,
      "visible": true,
      "fillin": false,
      "visited": false,
      "linkIdx": 3,
      "hintsIdx": -9999,
      "sentenceIdx": 3,
      "sectionIdx": 3
    },
    {
      "content": "0",
      "termIdx": 17,
      "nextTermIdx": [
        18
      ],
      "prevTermIdx": [
        16
      ],
      "altpronunciation": "",
      "altrecognition": "zero",
      "recitable": true,
      "audible": true,
      "linkable": false,
      "visible": true,
      "fillin": false,
      "visited": false,
      "linkIdx": 3,
      "hintsIdx": -9999,
      "sentenceIdx": 3,
      "sectionIdx": 3
    },
    {
      "content": "8",
      "termIdx": 18,
      "nextTermIdx": [
        19
      ],
      "prevTermIdx": [
        17
      ],
      "altpronunciation": "",
      "altrecognition": "",
      "recitable": true,
      "audible": true,
      "linkable": false,
      "visible": true,
      "fillin": false,
      "visited": false,
      "linkIdx": 3,
      "hintsIdx": -9999,
      "sentenceIdx": 3,
      "sectionIdx": 3
    },
    {
      "content": "2",
      "termIdx": 19,
      "nextTermIdx": [
        20
      ],
      "prevTermIdx": [
        18
      ],
      "altpronunciation": "",
      "altrecognition": "",
      "recitable": true,
      "audible": true,
      "linkable": false,
      "visible": true,
      "fillin": false,
      "visited": false,
      "linkIdx": 3,
      "hintsIdx": -9999,
      "sentenceIdx": 3,
      "sectionIdx": 3
    },
    {
      "content": "6",
      "termIdx": 20,
      "nextTermIdx": [
        21
      ],
      "prevTermIdx": [
        19
      ],
      "altpronunciation": "",
      "altrecognition": "",
      "recitable": true,
      "audible": true,
      "linkable": false,
      "visible": true,
      "fillin": false,
      "visited": false,
      "linkIdx": 3,
      "hintsIdx": -9999,
      "sentenceIdx": 3,
      "sectionIdx": 3
    },
    {
      "content": "7",
      "termIdx": 21,
      "nextTermIdx": [
        22
      ],
      "prevTermIdx": [
        20
      ],
      "altpronunciation": "",
      "altrecognition": "",
      "recitable": true,
      "audible": true,
      "linkable": false,
      "visible": true,
      "fillin": false,
      "visited": false,
      "linkIdx": 3,
      "hintsIdx": -9999,
      "sentenceIdx": 3,
      "sectionIdx": 3
    },
    {
      "content": "6",
      "termIdx": 22,
      "nextTermIdx": [
        23
      ],
      "prevTermIdx": [
        21
      ],
      "altpronunciation": "",
      "altrecognition": "",
      "recitable": true,
      "audible": true,
      "linkable": false,
      "visible": true,
      "fillin": false,
      "visited": false,
      "linkIdx": 3,
      "hintsIdx": -9999,
      "sentenceIdx": 3,
      "sectionIdx": 3
    },
    {
      "content": "0",
      "termIdx": 23,
      "nextTermIdx": [
        24
      ],
      "prevTermIdx": [
        22
      ],
      "altpronunciation": "",
      "altrecognition": "zero",
      "recitable": true,
      "audible": true,
      "linkable": false,
      "visible": true,
      "fillin": false,
      "visited": false,
      "linkIdx": 3,
      "hintsIdx": -9999,
      "sentenceIdx": 3,
      "sectionIdx": 3
    },
    {
      "content": "7",
      "termIdx": 24,
      "nextTermIdx": [
        25
      ],
      "prevTermIdx": [
        23
      ],
      "altpronunciation": "",
      "altrecognition": "",
      "recitable": true,
      "audible": true,
      "linkable": false,
      "visible": true,
      "fillin": false,
      "visited": false,
      "linkIdx": 3,
      "hintsIdx": -9999,
      "sentenceIdx": 3,
      "sectionIdx": 3
    },
    {
      "content": "6",
      "termIdx": 25,
      "nextTermIdx": [
        26
      ],
      "prevTermIdx": [
        24
      ],
      "altpronunciation": "",
      "altrecognition": "",
      "recitable": true,
      "audible": true,
      "linkable": false,
      "visible": true,
      "fillin": false,
      "visited": false,
      "linkIdx": 3,
      "hintsIdx": -9999,
      "sentenceIdx": 3,
      "sectionIdx": 3
    },
    {
      "content": "the",
      "termIdx": 26,
      "nextTermIdx": [],
      "prevTermIdx": [
        25
      ],
      "altpronunciation": "",
      "altrecognition": "",
      "recitable": true,
      "audible": true,
      "linkable": false,
      "visible": true,
      "fillin": false,
      "visited": false,
      "linkIdx": -9999,
      "hintsIdx": -9999,
      "sentenceIdx": 3,
      "sectionIdx": 3
    }
  ],
  "headingList": [],
  "sectionList": [
    {
      "firstTermIdx": 0,
      "lastTermIdx": 6,
      "type": "paragraph"
    },
    {
      "firstTermIdx": 7,
      "lastTermIdx": 10,
      "type": "paragraph"
    },
    {
      "firstTermIdx": 11,
      "lastTermIdx": 15,
      "type": "paragraph"
    },
    {
      "firstTermIdx": 16,
      "lastTermIdx": 26,
      "type": "paragraph"
    }
  ],
  "sentenceList": [
    {
      "firstTermIdx": 0,
      "lastTermIdx": 6,
      "lastPunctuation": ""
    },
    {
      "firstTermIdx": 7,
      "lastTermIdx": 10,
      "lastPunctuation": ""
    },
    {
      "firstTermIdx": 11,
      "lastTermIdx": 15,
      "lastPunctuation": ""
    },
    {
      "firstTermIdx": 16,
      "lastTermIdx": 26,
      "lastPunctuation": ""
    }
  ],
  "linkList": [
    {
      "destination": "link2",
      "sectionIdx": 6,
      "terminalIdx": -9999,
      "valid": true
    },
    {
      "destination": "test2",
      "sectionIdx": 1,
      "terminalIdx": -9999,
      "valid": true
    },
    {
      "destination": "test2",
      "sectionIdx": -9999,
      "terminalIdx": -9999,
      "valid": true
    },
    {
      "destination": "",
      "sectionIdx": 13,
      "terminalIdx": -9999,
      "valid": true
    }
  ]
}